codebase_rag/__init__.py
codebase_rag/config.py
codebase_rag/embedder.py
codebase_rag/graph_loader.py
codebase_rag/graph_updater.py
codebase_rag/language_config.py
codebase_rag/main.py
codebase_rag/parser_loader.py
codebase_rag/prompts.py
codebase_rag/schemas.py
codebase_rag/unixcoder.py
codebase_rag/vector_store.py
codec/__init__.py
codec/schema_pb2.py
codec/schema_pb2.pyi
mseep_graph_code-0.0.24.dist-info/licenses/LICENSE
mseep_graph_code-0.0.24.dist-info/METADATA
mseep_graph_code-0.0.24.dist-info/WHEEL
mseep_graph_code-0.0.24.dist-info/entry_points.txt
mseep_graph_code-0.0.24.dist-info/top_level.txt
mseep_graph_code-0.0.24.dist-info/RECORD
