Metadata-Version: 2.4
Name: mseep-graph-code
Version: 0.0.24
Summary: Add your description here
Author-email: mseep <support@skydeck.ai>
Requires-Python: >=3.12
License-File: LICENSE
Requires-Dist: loguru>=0.7.3
Requires-Dist: mcp>=1.21.1
Requires-Dist: pydantic-ai>=1.27.0
Requires-Dist: pydantic-settings>=2.0.0
Requires-Dist: pymgclient>=1.4.0
Requires-Dist: python-dotenv>=1.1.0
Requires-Dist: toml>=0.10.2
Requires-Dist: tree-sitter-python>=0.23.6
Requires-Dist: tree-sitter==0.25.0
Requires-Dist: watchdog>=6.0.0
Requires-Dist: typer>=0.12.5
Requires-Dist: rich>=13.7.1
Requires-Dist: prompt-toolkit>=3.0.0
Requires-Dist: diff-match-patch>=20241021
Requires-Dist: click>=8.0.0
Requires-Dist: pytest-xdist>=3.8.0
Requires-Dist: protobuf>=5.27.0
Provides-Extra: test
Requires-Dist: pytest>=8.4.1; extra == "test"
Requires-Dist: pytest-asyncio>=1.0.0; extra == "test"
Provides-Extra: dev
Requires-Dist: ruff>=0.5.5; extra == "dev"
Requires-Dist: ty>=0.0.1a32; extra == "dev"
Requires-Dist: pre-commit>=4.2.0; extra == "dev"
Requires-Dist: types-protobuf>=5.0.0; extra == "dev"
Provides-Extra: treesitter-full
Requires-Dist: tree-sitter-python>=0.23.6; extra == "treesitter-full"
Requires-Dist: tree-sitter-javascript>=0.23.1; extra == "treesitter-full"
Requires-Dist: tree-sitter-typescript>=0.23.2; extra == "treesitter-full"
Requires-Dist: tree-sitter-rust>=0.24.0; extra == "treesitter-full"
Requires-Dist: tree-sitter-go>=0.23.4; extra == "treesitter-full"
Requires-Dist: tree-sitter-scala>=0.24.0; extra == "treesitter-full"
Requires-Dist: tree-sitter-java>=0.23.5; extra == "treesitter-full"
Requires-Dist: tree-sitter-cpp>=0.23.0; extra == "treesitter-full"
Requires-Dist: tree-sitter-lua>=0.0.19; extra == "treesitter-full"
Provides-Extra: semantic
Requires-Dist: qdrant-client>=1.9.0; extra == "semantic"
Requires-Dist: torch>=2.6.0; extra == "semantic"
Requires-Dist: transformers>=4.0.0; extra == "semantic"
Dynamic: license-file
